src/__init__.py
src/config.py
src/cranecloud/__init__.py
src/cranecloud/commands/__init__.py
src/cranecloud/commands/apps.py
src/cranecloud/commands/clusters.py
src/cranecloud/commands/projects.py
src/cranecloud/commands/test_user_management.py
src/cranecloud/commands/user_management.py
src/cranecloud/helpers/__init__.py
cranecloud_test-0.0.1.dist-info/LICENSE
cranecloud_test-0.0.1.dist-info/METADATA
cranecloud_test-0.0.1.dist-info/WHEEL
cranecloud_test-0.0.1.dist-info/entry_points.txt
cranecloud_test-0.0.1.dist-info/top_level.txt
cranecloud_test-0.0.1.dist-info/RECORD
