Metadata-Version: 2.1
Name: cranecloud-test
Version: 0.0.1
Summary: Cranecloud CLI client
Author-email: cranecloud <allan@cranecloud.io>
Project-URL: Homepage, https://github.com/crane-cloud/cranecloud-cli
Project-URL: Issues, https://github.com/crane-cloud/cranecloud-cli/issues
Classifier: Programming Language :: Python :: 3
Classifier: License :: OSI Approved :: MIT License
Classifier: Operating System :: OS Independent
Requires-Python: >=3.8
License-File: LICENSE
Requires-Dist: Click
Requires-Dist: requests
Requires-Dist: keyring ==24.3.0
Requires-Dist: tabulate
Requires-Dist: colorama
Requires-Dist: Pygments
Requires-Dist: rich
Requires-Dist: python-dotenv
Requires-Dist: urllib3 ==2.1.0
Requires-Dist: toml ==0.10.2
Provides-Extra: dev
Requires-Dist: twine ; extra == 'dev'
Requires-Dist: pip-tools ; extra == 'dev'
Requires-Dist: pytest ; extra == 'dev'
